harvester.py
core/__init__.py
core/batch_processor.py
core/collector.py
core/csv_scanner.py
core/document_loader.py
core/function_calling.py
core/json_template_processor.py
core/post_processor.py
core/result_templater.py
core/rqp_templater.py
core/scanner.py
core/structured_output.py
core/synthesizer.py
core/template_adapter.py
core/templater.py
harvester_sdk/__init__.py
harvester_sdk/output_manager.py
harvester_sdk/sdk.py
harvester_sdk-2.1.2.dist-info/licenses/LICENSE
processors/__init__.py
processors/batch_submitter.py
processors/galactic_federation.py
processors/gemini_batch_submitter.py
processors/multi_provider_parallel.py
processors/parallel.py
processors/parallel_monarchy.py
processors/xai_async_processor.py
processors/xai_deferred_submitter.py
providers/__init__.py
providers/anthropic_provider.py
providers/base_provider.py
providers/dalle3_provider.py
providers/deepseek_provider.py
providers/gemini_exp_provider.py
providers/gemini_provider.py
providers/genai_embeddings_provider.py
providers/genai_functions_provider.py
providers/genai_imagen_provider.py
providers/genai_lyria_provider.py
providers/genai_provider.py
providers/genai_tts_provider.py
providers/genai_veo3_provider.py
providers/generic_provider.py
providers/google_provider.py
providers/gpt_image_provider.py
providers/openai_image_provider.py
providers/openai_provider.py
providers/provider_factory.py
providers/rqp_adapter.py
providers/vertex_image_provider.py
providers/vertex_provider.py
providers/xai_async.py
providers/xai_batch_provider.py
providers/xai_functions.py
providers/xai_image_provider.py
providers/xai_provider.py
providers/xai_provider_advanced.py
providers/xai_streaming.py
utils/__init__.py
utils/file_handlers.py
utils/json_csv_converter.py
utils/output_manager.py
utils/output_paths.py
utils/progress_tracker.py
utils/rate_limiter.py
harvester_sdk-2.1.2.dist-info/METADATA
harvester_sdk-2.1.2.dist-info/WHEEL
harvester_sdk-2.1.2.dist-info/entry_points.txt
harvester_sdk-2.1.2.dist-info/top_level.txt
harvester_sdk-2.1.2.dist-info/RECORD
