Metadata-Version: 2.4
Name: harvester-sdk
Version: 2.1.2
Summary: Harvester SDK - The Complete AI Processing Platform with Agentic Coding Assistants. Unified interface for all AI processing paradigms with enterprise-grade reliability.
Home-page: https://github.com/quantum-encoding/harvester-sdk
Author: Quantum Encoding Ltd
Author-email: Quantum Encoding Ltd <rich@quantumencoding.io>
Maintainer-email: "Rich (The Architect)" <rich@quantumencoding.io>
License: LicenseRef-Proprietary
Project-URL: Homepage, https://quantumencoding.io
Project-URL: Documentation, https://github.com/quantum-encoding/harvester-sdk
Project-URL: Repository, https://github.com/quantum-encoding/harvester-sdk
Project-URL: Issues, https://github.com/quantum-encoding/harvester-sdk/issues
Project-URL: PyPI, https://pypi.org/project/harvester-sdk/
Keywords: ai,parallel-processing,batch-processing,openai,anthropic,google-ai,vertex-ai,genai,gemini,xai,grok,deepseek,multi-provider,async,sdk,harvesting-engine,automation,turn-based-chat,non-streaming,agentic,agents,coding-assistant,claude-agent-sdk
Classifier: Development Status :: 5 - Production/Stable
Classifier: Intended Audience :: Developers
Classifier: Topic :: Software Development :: Libraries :: Python Modules
Classifier: Topic :: Scientific/Engineering :: Artificial Intelligence
Classifier: Programming Language :: Python :: 3
Classifier: Programming Language :: Python :: 3.8
Classifier: Programming Language :: Python :: 3.9
Classifier: Programming Language :: Python :: 3.10
Classifier: Programming Language :: Python :: 3.11
Classifier: Programming Language :: Python :: 3.12
Classifier: Operating System :: OS Independent
Classifier: Framework :: AsyncIO
Requires-Python: >=3.8
License-File: LICENSE
Requires-Dist: aiohttp>=3.8.0
Requires-Dist: aiofiles>=23.0.0
Requires-Dist: jinja2>=3.0.0
Requires-Dist: pyyaml>=6.0
Requires-Dist: python-dotenv>=1.0.0
Requires-Dist: tqdm>=4.65.0
Requires-Dist: click>=8.0.0
Requires-Dist: pandas>=2.0.0
Requires-Dist: pillow>=10.0.0
Requires-Dist: openai>=1.0.0
Requires-Dist: anthropic>=0.65.0
Requires-Dist: claude-agent-sdk>=0.1.0
Requires-Dist: google-generativeai>=0.8.0
Provides-Extra: openai
Requires-Dist: openai>=1.0.0; extra == "openai"
Provides-Extra: anthropic
Requires-Dist: anthropic>=0.3.0; extra == "anthropic"
Provides-Extra: genai
Requires-Dist: google-genai>=0.1.0; extra == "genai"
Provides-Extra: google
Requires-Dist: google-generativeai>=0.3.0; extra == "google"
Provides-Extra: vertex
Requires-Dist: google-cloud-aiplatform>=1.38.0; extra == "vertex"
Provides-Extra: xai
Requires-Dist: openai>=1.0.0; extra == "xai"
Provides-Extra: deepseek
Requires-Dist: openai>=1.0.0; extra == "deepseek"
Provides-Extra: all
Requires-Dist: openai>=1.0.0; extra == "all"
Requires-Dist: anthropic>=0.3.0; extra == "all"
Requires-Dist: google-genai>=0.1.0; extra == "all"
Requires-Dist: google-generativeai>=0.3.0; extra == "all"
Requires-Dist: google-cloud-aiplatform>=1.38.0; extra == "all"
Provides-Extra: dev
Requires-Dist: pytest>=7.0.0; extra == "dev"
Requires-Dist: pytest-asyncio>=0.21.0; extra == "dev"
Requires-Dist: black>=23.0.0; extra == "dev"
Requires-Dist: ruff>=0.1.0; extra == "dev"
Requires-Dist: mypy>=1.0.0; extra == "dev"
Requires-Dist: coverage>=7.0.0; extra == "dev"
Provides-Extra: docs
Requires-Dist: sphinx>=4.0.0; extra == "docs"
Requires-Dist: sphinx-rtd-theme>=1.0.0; extra == "docs"
Requires-Dist: myst-parser>=0.18.0; extra == "docs"
Dynamic: author
Dynamic: home-page
Dynamic: license-file
Dynamic: requires-python
